
<ObjectSpec>
<SpecVersion>15_0_9-121631</SpecVersion>
<Object>
<ObjClsGuid>c9584656-94b6-4ccd-890f-332d11fc2c25</ObjClsGuid>
<ObjCls>13</ObjCls>
<ObjId>18</ObjId>
<ObjName>GAMExampleLogin</ObjName>
<ObjDesc>Login</ObjDesc>
<ObjPgmName>GAMExampleLogin</ObjPgmName>
<ObjClsName>Web Panel</ObjClsName></Object>
<Result>genreq</Result>
<Warnings></Warnings>
<Errors></Errors>
<Generator>
<GenId>15</GenId>
<GenName>Default (C#)</GenName></Generator>
<FormClass>HTML</FormClass>
<Parameters></Parameters>
<StandAloneRules></StandAloneRules>
<Event>
<EventName>Start</EventName></Event>
<Event>
<EventName>Enter</EventName>
<Level>
<Optimizations></Optimizations>
<LevelType>For Each</LevelType>
<LevelBeginRow>53</LevelBeginRow>
<BaseTable>
<Table>
<TableId>3</TableId>
<TableName>Usuario</TableName>
<Description>Usuário</Description></Table></BaseTable>
<Order>
<Attribute>
<AttriId>11</AttriId>
<AttriName>UsuarioId</AttriName>
<Description>Id</Description></Attribute></Order>
<Condition></Condition>
<IndexName>IUSUARIO</IndexName>
<LevelOptions></LevelOptions>
<OptimizedWhere>
<StartFrom>
<Condition>
<Token>FirstRecord</Token></Condition></StartFrom>
<LoopWhile>
<Condition>
<Token>NotEndOfTable</Token></Condition></LoopWhile></OptimizedWhere>
<NonOptimizedWhere>
<Condition>
<Attribute>
<AttriId>54</AttriId>
<AttriName>UsuarioLogin</AttriName>
<Description>Login</Description></Attribute>
<Sp></Sp>
<Token>=</Token>
<Sp></Sp>
<Variable>
<VarId>Username</VarId>
<VarName>&amp;UserName</VarName></Variable></Condition>
<Condition>
<Attribute>
<AttriId>55</AttriId>
<AttriName>UsuarioSenha</AttriName>
<Description>Senha</Description></Attribute>
<Sp></Sp>
<Token>=</Token>
<Sp></Sp>
<Variable>
<VarId>Usuariosenhamd5</VarId>
<VarName>&amp;UsuarioSenhaMd5</VarName></Variable></Condition></NonOptimizedWhere>
<NavigationTree>
<Table>
<TableId>3</TableId>
<TableName>Usuario</TableName>
<Description>Usuário</Description>
<RecordsToRead>many</RecordsToRead>
<KeyAttributes>
<Attribute>
<AttriId>11</AttriId>
<AttriName>UsuarioId</AttriName>
<Description>Id</Description></Attribute></KeyAttributes>
<Into>
<Attribute>
<AttriId>55</AttriId>
<AttriName>UsuarioSenha</AttriName>
<Description>Senha</Description></Attribute>
<Attribute>
<AttriId>54</AttriId>
<AttriName>UsuarioLogin</AttriName>
<Description>Login</Description></Attribute>
<Attribute>
<AttriId>11</AttriId>
<AttriName>UsuarioId</AttriName>
<Description>Id</Description></Attribute>
<Attribute>
<AttriId>12</AttriId>
<AttriName>UsuarioNome</AttriName>
<Description>Nome</Description></Attribute></Into>
<Tables></Tables></Table></NavigationTree>
<TablesToUpdate></TablesToUpdate>
<Formulas>
<VerticalFormulas></VerticalFormulas>
<AggSelFormulas></AggSelFormulas></Formulas>
<CALL>
<Object>
<ObjClsGuid>84a12160-f59b-4ad7-a683-ea4481ac23e9</ObjClsGuid>
<ObjCls>1</ObjCls>
<ObjId>39</ObjId>
<ObjName>log</ObjName>
<ObjPgmName>log</ObjPgmName>
<ObjClsName>Procedure</ObjClsName></Object>
<Parameters>
<Token>&quot;entrou&quot;</Token></Parameters>
<IF></IF></CALL>
<CALL>
<Object>
<ObjClsGuid>84a12160-f59b-4ad7-a683-ea4481ac23e9</ObjClsGuid>
<ObjCls>1</ObjCls>
<ObjId>39</ObjId>
<ObjName>log</ObjName>
<ObjPgmName>log</ObjPgmName>
<ObjClsName>Procedure</ObjClsName></Object>
<Parameters>
<Token>&quot;usuarioid: &quot;</Token>
<Sp></Sp>
<Token>+</Token>
<Sp></Sp>
<Attribute>
<AttriId>11</AttriId>
<AttriName>UsuarioId</AttriName>
<Description>Id</Description></Attribute>
<Token>.</Token>
<Token>tostring(</Token>
<Sp></Sp>
<Token>18</Token>
<Token>,</Token>
<Sp></Sp>
<Token>0</Token>
<Token>)</Token></Parameters>
<IF></IF></CALL>
<CALL>
<Object>
<ObjClsGuid>84a12160-f59b-4ad7-a683-ea4481ac23e9</ObjClsGuid>
<ObjCls>1</ObjCls>
<ObjId>16</ObjId>
<ObjName>WWPBaseObjects.SetWWPContext</ObjName>
<ObjPgmName>WWPBaseObjects.SetWWPContext</ObjPgmName>
<ObjClsName>Procedure</ObjClsName></Object>
<Parameters>
<Variable>
<VarId>Wwpcontext</VarId>
<VarName>&amp;WWPContext</VarName></Variable></Parameters>
<IF></IF></CALL>
<CALL>
<Object>
<ObjClsGuid>c9584656-94b6-4ccd-890f-332d11fc2c25</ObjClsGuid>
<ObjCls>13</ObjCls>
<ObjId>82</ObjId>
<ObjName>HomeNew</ObjName>
<ObjPgmName>HomeNew</ObjPgmName>
<ObjClsName>Web Panel</ObjClsName></Object>
<Parameters></Parameters>
<IF></IF></CALL></Level></Event>
<Event>
<EventName>'ATTRIBUTESSECURITYCODE'</EventName>
<EventType>Subrutine</EventType></Event>
<Event>
<EventName>Refresh</EventName></Event>
<Event>
<EventName>Load</EventName></Event>
<Suggests></Suggests></ObjectSpec>